droplet-0.1.dist-info/METADATA
droplet-0.1.dist-info/WHEEL
droplet-0.1.dist-info/DESCRIPTION.rst
droplet-0.1.dist-info/entry_points.txt
droplet-0.1.dist-info/RECORD
droplet-0.1.dist-info/top_level.txt
droplet-0.1.dist-info/metadata.json
droplet/common.py
droplet/settings.py
droplet/catalog.py
droplet/__init__.py
droplet/sudo.py
droplet/apps.py
droplet/files.py
droplet/signals.py
droplet/test_settings.py
droplet/util.py
droplet/daemons.py
droplet/actions.py
droplet/database.py
droplet/module.py
droplet/commands.py
droplet/models.py
droplet/web/__init__.py
droplet/web/views.py
droplet/web/tables.py
droplet/web/menus.py
droplet/web/wsgi.py
droplet/web/wizards.py
droplet/web/urls.py
droplet/web/forms.py
droplet/web/static/fonts/glyphicons-halflings-regular.svg
droplet/web/static/fonts/glyphicons-halflings-regular.eot
droplet/web/static/fonts/glyphicons-halflings-regular.woff
droplet/web/static/fonts/glyphicons-halflings-regular.ttf
droplet/web/static/css/bootstrap-theme.css
droplet/web/static/css/bootstrap.css
droplet/web/static/css/bootstrap.min.css
droplet/web/static/css/style.css
droplet/web/static/css/bootstrap-theme.min.css
droplet/web/static/img/loading.gif
droplet/web/static/js/droplet.js
droplet/web/static/js/jquery.min.js
droplet/web/static/js/bootstrap.js
droplet/web/static/js/bootstrap.min.js
droplet/web/templates/web/form.html
droplet/web/templates/web/wizard.html
droplet/web/templates/web/base.html
droplet/web/templates/web/home.html
droplet/web/templates/web/form_edit.html
droplet/web/templates/web/table.html
droplet/interfaces/__init__.py
droplet/interfaces/samba.py
droplet/management/__init__.py
droplet/management/commands/__init__.py
droplet/management/commands/restart.py
droplet/management/commands/save.py
droplet/management/commands/stop.py
droplet/management/commands/start.py
droplet/network/__init__.py
droplet/network/util.py
droplet/network/urls.py
droplet/network/module.py
droplet/network/menu.py
droplet/network/forms.py
droplet/network/models.py
droplet/network/blocks.py
droplet/network/templates/interfaces
droplet/core/__init__.py
droplet/core/urls.py
droplet/core/actions.py
droplet/core/blocks.py
